toadbase/__init__.py
toadbase/toadbase.py
toadbase/models/__init__.py
toadbase/models/shotgrid.py
toadbase-0.0.4.dist-info/METADATA
toadbase-0.0.4.dist-info/WHEEL
toadbase-0.0.4.dist-info/top_level.txt
toadbase-0.0.4.dist-info/RECORD
