Metadata-Version: 2.4
Name: toadbase
Version: 0.0.4
Summary: Welcome to Toadbase, I love you
Author-email: A toad <a_literal_toad@toadbase.com>
License-Expression: MIT
Classifier: Programming Language :: Python :: 3
Classifier: Operating System :: OS Independent
Requires-Python: >=3.9
Requires-Dist: requests==2.32.5
Requires-Dist: pydantic==2.11.5
